README.rst
setup.py
LiveStreamingEnv/ABR.py
LiveStreamingEnv/__init__.py
LiveStreamingEnv/demo.py
LiveStreamingEnv/env.py
LiveStreamingEnv/final_env.py
LiveStreamingEnv/final_fixed_env.py
LiveStreamingEnv/fixed_env.py
LiveStreamingEnv/load_trace.py
LiveStreamingEnv/online.py
LiveStreamingEnv/pyparams.py
LiveStreamingEnv.egg-info/PKG-INFO
LiveStreamingEnv.egg-info/SOURCES.txt
LiveStreamingEnv.egg-info/dependency_links.txt
LiveStreamingEnv.egg-info/requires.txt
LiveStreamingEnv.egg-info/top_level.txt